todol/__init__.py
todol/main.py
todol/flags/__init__.py
todol/flags/todol_list.py
todol/flags/todol_path.py
todol/flags/todol_upgrade.py
todol/flags/todol_upgrades.py
todol/flags/todol_version.py
todol/functionality/__init__.py
todol/functionality/commands.py
todol/functionality/commands_list.py
todol/functionality/functions.py
todol/functionality/paths.py
todol/functionality/prompts.py
todol/functionality/shellcompleter.py
todol-0.3.5.dist-info/licenses/LICENSE
todol-0.3.5.dist-info/METADATA
todol-0.3.5.dist-info/WHEEL
todol-0.3.5.dist-info/entry_points.txt
todol-0.3.5.dist-info/top_level.txt
todol-0.3.5.dist-info/RECORD
