Metadata-Version: 2.4
Name: todol
Version: 0.3.5
Summary: A python TUI todo app
Requires-Python: >=3.9
License-File: LICENSE
Requires-Dist: prompt_toolkit>=3.0.52
Requires-Dist: platformdirs>=4.5.1
Requires-Dist: rich>=14.3.1
Requires-Dist: requests>=2.32.5
Dynamic: license-file
